wip_manager/cli.py
wip_manager-0.1.0.dist-info/LICENSE
wip_manager-0.1.0.dist-info/METADATA
wip_manager-0.1.0.dist-info/WHEEL
wip_manager-0.1.0.dist-info/entry_points.txt
wip_manager-0.1.0.dist-info/top_level.txt
wip_manager-0.1.0.dist-info/RECORD
