Metadata-Version: 2.1
Name: wip_manager
Version: 0.1.0
Summary: A CLI tool to manage wip branch with automated commit and merge
Author-email: Your Name <you@example.com>
License: MIT
Requires-Python: >=3.7
License-File: LICENSE
Requires-Dist: typer[all]
Requires-Dist: GitPython
Requires-Dist: watchdog
Requires-Dist: rich
Requires-Dist: pathspec
